PyDMath/SI_and_CI.py
PyDMath/__init__.py
PyDMath/divisor.py
PyDMath/lcm_and_hcf.py
PyDMath/mensuration.py
PyDMath/per_and_comb.py
PyDMath/time.py
PyDMath-0.3.dist-info/METADATA
PyDMath-0.3.dist-info/WHEEL
PyDMath-0.3.dist-info/top_level.txt
PyDMath-0.3.dist-info/RECORD
