Metadata-Version: 2.1
Name: PyDMath
Version: 0.3
Summary: Solving the maths problems
Author: Dhamodharan
Author-email: dhamodharan1888@gmail.com>
Keywords: python,math,problems,mathematics,scientific calculations
Classifier: Development Status :: 2 - Pre-Alpha
Classifier: Intended Audience :: Developers
Classifier: Programming Language :: Python :: 3
Classifier: Operating System :: Unix
Classifier: Operating System :: MacOS :: MacOS X
Classifier: Operating System :: Microsoft :: Windows
Requires-Dist: numpy
